typer_common_functions/__init__.py
typer_common_functions/logging.py
typer_common_functions/typer.py
typer_common_functions-0.1.2.dist-info/METADATA
typer_common_functions-0.1.2.dist-info/WHEEL
typer_common_functions-0.1.2.dist-info/licenses/LICENSE
typer_common_functions-0.1.2.dist-info/RECORD
