Metadata-Version: 2.4
Name: typer-common-functions
Version: 0.1.2
Summary: Commonly used Functions around the Typer CLI Library
Project-URL: homepage, https://pypi.org/project/typer-common-functions/
Project-URL: repository, https://github.com/OpenJKSoftware/typer-common-functions
Author-email: Joshua Kreuder <joshua_kreuder@outlook.com>
License-Expression: LGPL-3.0-or-later
License-File: LICENSE
Keywords: cli,typer
Requires-Python: >=3.8
Requires-Dist: rich>=10.0.0
Requires-Dist: shellingham>=1.5.0
Requires-Dist: typer>=0.7.0
